{
  "operation": "UserServiceProviderQuery",
  "response": {
    "data": {
      "helloproject": {
        "artists": [
          {
            "id": "1",
            "key": "morningmusume",
            "name": "モーニング娘。'24",
            "thumbnailURL": "http://cdn.helloproject.com/img/artist/m/638f37526b1e6cbadfcf3521d2b451ae34dd237e.jpg",
            "members": [
              {
                "id": "8589934592",
                "key": "mizuki_fukumura",
                "artistKey": "morningmusume",
                "name": "譜久村聖",
                "nameKana": "フクムラミズキ",
                "thumbnailURL": "http://cdn.helloproject.com/img/artist/m/8bf17e09fa5cb3e62ad57617c81e1b6c8f9958f6.jpg",
                "dateOfBirth": "1996-10-29T15:00:00Z",
                "bloodType": "O",
                "joinAt": "2011-01-01T15:00:00Z",
                "graduateAt": "2023-11-30T23:59:59Z"
              },
              {
                "id": "8589934593",
                "key": "erina_ikuta",
                "artistKey": "morningmusume",
                "name": "生田衣梨奈",
                "nameKana": "イクタエリナ",
                "thumbnailURL": "http://cdn.helloproject.com/img/artist/m/ab985f537669471aa614d049e228e3d49b7ed43f.jpg",
                "dateOfBirth": "1997-07-06T15:00:00Z",
                "bloodType": "A",
                "joinAt": "2011-01-01T15:00:00Z",
                "graduateAt": null
              },
              {
                "id": "8589934594",
                "key": "ayumi_ishida",
                "artistKey": "morningmusume",
                "name": "石田亜佑美",
                "nameKana": "イシダアユミ",
                "thumbnailURL": "http://cdn.helloproject.com/img/artist/m/be0973bcedf729798495d0aa35b392550ff9ad0f.jpg",
                "dateOfBirth": "1997-01-06T15:00:00Z",
                "bloodType": "O",
                "joinAt": "2011-09-28T15:00:00Z",
                "graduateAt": null
              },
              {
                "id": "8589934595",
                "key": "masaki_satou",
                "artistKey": "morningmusume",
                "name": "佐藤優樹",
                "nameKana": "サトウマサキ",
                "thumbnailURL": "http://cdn.helloproject.com/img/artist/m/c28f02d1a45bb3b97a6dd5c6431a9ddd5bacc92b.jpg",
                "dateOfBirth": "1999-05-06T15:00:00Z",
                "bloodType": "A",
                "joinAt": "2011-09-28T15:00:00Z",
                "graduateAt": "2021-12-14T23:59:59Z"
              },
              {
                "id": "8589934596",
                "key": "sakura_oda",
                "artistKey": "morningmusume",
                "name": "小田さくら",
                "nameKana": "オダサクラ",
                "thumbnailURL": "http://cdn.helloproject.com/img/artist/m/79d41318d94a8ae510340a3eb8de894a7b6286a9.jpg",
                "dateOfBirth": "1999-03-11T15:00:00Z",
                "bloodType": "A",
                "joinAt": "2012-09-13T15:00:00Z",
                "graduateAt": null
              },
              {
                "id": "8589934597",
                "key": "miki_nonaka",
                "artistKey": "morningmusume",
                "name": "野中美希",
                "nameKana": "ノナカミキ",
                "thumbnailURL": "http://cdn.helloproject.com/img/artist/m/f389bc271fbd69871cc22a461ab9c5c45a394fed.jpg",
                "dateOfBirth": "1999-10-06T15:00:00Z",
                "bloodType": "A",
                "joinAt": "2014-09-29T15:00:00Z",
                "graduateAt": null
              },
              {
                "id": "8589934598",
                "key": "maria_makino",
                "artistKey": "morningmusume",
                "name": "牧野真莉愛",
                "nameKana": "マキノマリア",
                "thumbnailURL": "http://cdn.helloproject.com/img/artist/m/0060196d6e786107db3de5ffe823c7c5e5f2512e.jpg",
                "dateOfBirth": "2001-02-01T15:00:00Z",
                "bloodType": "A",
                "joinAt": "2014-09-29T15:00:00Z",
                "graduateAt": null
              },
              {
                "id": "8589934599",
                "key": "akane_haga",
                "artistKey": "morningmusume",
                "name": "羽賀朱音",
                "nameKana": "ハガアカネ",
                "thumbnailURL": "http://cdn.helloproject.com/img/artist/m/61814011a569ff0deae8bce18ee34f78361dfa7d.jpg",
                "dateOfBirth": "2002-03-06T15:00:00Z",
                "bloodType": "O",
                "joinAt": "2014-09-29T15:00:00Z",
                "graduateAt": null
              },
              {
                "id": "8589934600",
                "key": "kaede_kaga",
                "artistKey": "morningmusume",
                "name": "加賀楓",
                "nameKana": "カガカエデ",
                "thumbnailURL": "http://cdn.helloproject.com/img/artist/m/06e556832d22b4579a9c72caed347fc447f67443.jpg",
                "dateOfBirth": "1999-11-29T15:00:00Z",
                "bloodType": "A",
                "joinAt": "2016-12-11T15:00:00Z",
                "graduateAt": "2022-12-12T23:59:59Z"
              },
              {
                "id": "8589934601",
                "key": "reina_yokoyama",
                "artistKey": "morningmusume",
                "name": "横山玲奈",
                "nameKana": "ヨコヤマレイナ",
                "thumbnailURL": "http://cdn.helloproject.com/img/artist/m/358788eb469fb9917ac8074056db6b4096d36d4a.jpg",
                "dateOfBirth": "2001-02-21T15:00:00Z",
                "bloodType": "O",
                "joinAt": "2016-12-11T15:00:00Z",
                "graduateAt": null
              },
              {
                "id": "8589934602",
                "key": "chisaki_morito_m",
                "artistKey": "morningmusume",
                "name": "森戸知沙希",
                "nameKana": "モリトチサキ",
                "thumbnailURL": "http://cdn.helloproject.com/img/artist/m/3a1fc2e04f0254a18f857a8809963c2fc8f8ffad.jpg",
                "dateOfBirth": "2000-02-18T15:00:00Z",
                "bloodType": "A",
                "joinAt": "2014-11-04T15:00:00Z",
                "graduateAt": "2022-06-21T23:59:59Z"
              },
              {
                "id": "8589934603",
                "key": "rio_kitagawa",
                "artistKey": "morningmusume",
                "name": "北川莉央",
                "nameKana": "キタガワリオ",
                "thumbnailURL": "http://cdn.helloproject.com/img/artist/m/5d3e3df5aab14d7b58de16b63efbbe9edb63b14e.jpg",
                "dateOfBirth": "2004-03-15T15:00:00Z",
                "bloodType": "O",
                "joinAt": "2019-06-21T15:00:00Z",
                "graduateAt": null
              },
              {
                "id": "8589934604",
                "key": "homare_okamura",
                "artistKey": "morningmusume",
                "name": "岡村ほまれ",
                "nameKana": "オカムラホマレ",
                "thumbnailURL": "http://cdn.helloproject.com/img/artist/m/4abe532d1b0aad1212fb59cc9ef0009b5f8c5582.jpg",
                "dateOfBirth": "2005-05-08T15:00:00Z",
                "bloodType": "A",
                "joinAt": "2019-06-21T15:00:00Z",
                "graduateAt": null
              },
              {
                "id": "8589934605",
                "key": "mei_yamazaki",
                "artistKey": "morningmusume",
                "name": "山﨑愛生",
                "nameKana": "ヤマザキメイ",
                "thumbnailURL": "http://cdn.helloproject.com/img/artist/m/c77ffa2b44a590521290d5190e1c6db2deb26e22.jpg",
                "dateOfBirth": "2005-06-27T15:00:00Z",
                "bloodType": "B",
                "joinAt": "2019-06-21T15:00:00Z",
                "graduateAt": null
              },
              {
                "id": "8589934655",
                "key": "riho_sayashi",
                "artistKey": "morningmusume",
                "name": "鞘師里保",
                "nameKana": "サヤシリホ",
                "thumbnailURL": "https://wao-entertainment.com/wp-content/uploads/2018/12/SS-2018-12-08-9.06.08.jpg",
                "dateOfBirth": "1998-05-27T15:00:00Z",
                "bloodType": "AB",
                "joinAt": "2012-01-01T15:00:00Z",
                "graduateAt": "2015-12-30T15:00:00Z"
              },
              {
                "id": "8589934656",
                "key": "kanon_suzuki",
                "artistKey": "morningmusume",
                "name": "鈴木香音",
                "nameKana": "スズキカノン",
                "thumbnailURL": "https://pbs.twimg.com/media/CgpjYliU4AMA3EB?format=jpg&name=small",
                "dateOfBirth": "1998-08-04T15:00:00Z",
                "bloodType": "B",
                "joinAt": "2012-01-01T15:00:00Z",
                "graduateAt": "2016-05-30T15:00:00Z"
              },
              {
                "id": "8589934657",
                "key": "haruna_iikubo",
                "artistKey": "morningmusume",
                "name": "飯窪春菜",
                "nameKana": "イイクボハルナ",
                "thumbnailURL": "http://saraca.mokuren.ne.jp/mem/g/c201805-mm-03.jpg",
                "dateOfBirth": "1994-11-06T15:00:00Z",
                "bloodType": "O",
                "joinAt": "2011-09-28T15:00:00Z",
                "graduateAt": "2018-12-15T15:00:00Z"
              },
              {
                "id": "8589934658",
                "key": "haruka_kudo",
                "artistKey": "morningmusume",
                "name": "工藤遥",
                "nameKana": "クドウハルカ",
                "thumbnailURL": "https://cdn-ak.f.st-hatena.com/images/fotolife/r/risacchi/20171104/20171104000854.jpg",
                "dateOfBirth": "1999-10-26T15:00:00Z",
                "bloodType": "A",
                "joinAt": "2011-09-28T15:00:00Z",
                "graduateAt": "2017-12-10T15:00:00Z"
              },
              {
                "id": "8589934659",
                "key": "haruna_ogata",
                "artistKey": "morningmusume",
                "name": "尾形春水",
                "nameKana": "オガタハルナ",
                "thumbnailURL": "https://sunshine-sakae.jp/img02/image/818.jpg",
                "dateOfBirth": "1999-02-14T15:00:00Z",
                "bloodType": "A",
                "joinAt": "2014-09-29T15:00:00Z",
                "graduateAt": "2018-06-19T15:00:00Z"
              },
              {
                "id": "8590222510",
                "key": "rio_sakurai",
                "artistKey": "morningmusume",
                "name": "櫻井梨央",
                "nameKana": "サクライリオ",
                "thumbnailURL": "http://cdn.helloproject.com/img/artist/m/ea5cd447cd1d7614da0e3f8579dcc591d4f3fc06.jpg",
                "dateOfBirth": "2005-11-10T15:00:00Z",
                "bloodType": "O",
                "joinAt": "2022-06-28T15:00:00Z",
                "graduateAt": null
              },
              {
                "id": "8590786238",
                "key": "haruka_inoue",
                "artistKey": "morningmusume",
                "name": "井上春華",
                "nameKana": "イノウエハルカ",
                "thumbnailURL": "http://cdn.helloproject.com/img/artist/m/4a474f54a21fe53182a84ff8202ed0c36e9cff67.jpg",
                "dateOfBirth": "2006-05-05T15:00:00Z",
                "bloodType": "A",
                "joinAt": "2023-05-22T15:00:00Z",
                "graduateAt": null
              },
              {
                "id": "8590786239",
                "key": "ako_yumigeta",
                "artistKey": "morningmusume",
                "name": "弓桁朱琴",
                "nameKana": "ユミゲタアコ",
                "thumbnailURL": "http://cdn.helloproject.com/img/artist/m/f7555a0a2273db346b507d7e7c872a95c936d6f7.jpg",
                "dateOfBirth": "2008-07-07T15:00:00Z",
                "bloodType": "A",
                "joinAt": "2023-05-22T15:00:00Z",
                "graduateAt": null
              }
            ]
          },
          {
            "id": "2",
            "key": "angerme",
            "name": "アンジュルム",
            "thumbnailURL": "http://cdn.helloproject.com/img/artist/m/c9a28423a8314236a69313cfdfe7728cf9e11f88.jpg",
            "members": [
              {
                "id": "8589934606",
                "key": "akari_takeuchi",
                "artistKey": "angerme",
                "name": "竹内朱莉",
                "nameKana": "タケウチアカリ",
                "thumbnailURL": "http://cdn.helloproject.com/img/artist/m/8f6e0c19b53350d6c39d1e1d9d2c589f99a139b9.jpg",
                "dateOfBirth": "1997-11-22T15:00:00Z",
                "bloodType": "O",
                "joinAt": "2011-08-13T15:00:00Z",
                "graduateAt": "2023-06-22T23:59:59Z"
              },
              {
                "id": "8589934607",
                "key": "kana_nakanishi",
                "artistKey": "angerme",
                "name": "中西香菜",
                "nameKana": "ナカニシカナ",
                "thumbnailURL": "http://cdn.helloproject.com/img/artist/m/d432937b7d73553154eb0376984f69f68c85fb2c.jpg",
                "dateOfBirth": "1997-06-03T15:00:00Z",
                "bloodType": "A",
                "joinAt": "2011-08-13T15:00:00Z",
                "graduateAt": "2019-12-09T15:00:00Z"
              },
              {
                "id": "8589934608",
                "key": "ayano_kawamura",
                "artistKey": "angerme",
                "name": "川村文乃",
                "nameKana": "カワムラアヤノ",
                "thumbnailURL": "http://cdn.helloproject.com/img/artist/m/f74dcadc28ea1aed1f3115923dfc0ad535e37539.jpg",
                "dateOfBirth": "1999-07-06T15:00:00Z",
                "bloodType": "A",
                "joinAt": "2017-06-25T15:00:00Z",
                "graduateAt": null
              },
              {
                "id": "8589934609",
                "key": "mizuki_murota",
                "artistKey": "angerme",
                "name": "室田瑞希",
                "nameKana": "ムロタミズキ",
                "thumbnailURL": "http://cdn.helloproject.com/img/artist/m/e96c5b700569d80f4b1a7faafa3f4aa7d2e1825d.jpg",
                "dateOfBirth": "1998-06-11T15:00:00Z",
                "bloodType": "AB",
                "joinAt": "2014-10-03T15:00:00Z",
                "graduateAt": "2020-03-23T23:59:59Z"
              },
              {
                "id": "8589934610",
                "key": "rikako_sasaki",
                "artistKey": "angerme",
                "name": "佐々木莉佳子",
                "nameKana": "ササキリカコ",
                "thumbnailURL": "http://cdn.helloproject.com/img/artist/m/ac7a97007a64dde0b580efdca18d0335a2ca9275.jpg",
                "dateOfBirth": "2001-05-27T15:00:00Z",
                "bloodType": "A",
                "joinAt": "2014-10-03T15:00:00Z",
                "graduateAt": "2024-06-20T23:59:59Z"
              },
              {
                "id": "8589934611",
                "key": "moe_kamikokuryo",
                "artistKey": "angerme",
                "name": "上國料萌衣",
                "nameKana": "カミコクリョウモエ",
                "thumbnailURL": "http://cdn.helloproject.com/img/artist/m/7554d3717b74f40bc8b588550fe191a72f5be986.jpg",
                "dateOfBirth": "1999-10-23T15:00:00Z",
                "bloodType": "O",
                "joinAt": "2015-11-10T15:00:00Z",
                "graduateAt": null
              },
              {
                "id": "8589934612",
                "key": "momona_kasahara",
                "artistKey": "angerme",
                "name": "笠原桃奈",
                "nameKana": "カサハラモモナ",
                "thumbnailURL": "http://cdn.helloproject.com/img/artist/m/af37b232f383c2c746d8d2d5fa4ad8b203bae8b2.jpg",
                "dateOfBirth": "2003-10-21T15:00:00Z",
                "bloodType": "A",
                "joinAt": "2016-07-15T15:00:00Z",
                "graduateAt": "2021-11-16T23:59:59Z"
              },
              {
                "id": "8589934613",
                "key": "musubu_funaki_a",
                "artistKey": "angerme",
                "name": "船木結",
                "nameKana": "フナキムスブ",
                "thumbnailURL": "http://cdn.helloproject.com/img/artist/m/38f312f66bdce6cff3f8c8fae7c426394b2d3490.jpg",
                "dateOfBirth": "2002-05-09T15:00:00Z",
                "bloodType": "O",
                "joinAt": "2017-06-25T15:00:00Z",
                "graduateAt": "2020-12-10T23:59:59Z"
              },
              {
                "id": "8589934614",
                "key": "haruka_oota",
                "artistKey": "angerme",
                "name": "太田遥香",
                "nameKana": "オオタハルカ",
                "thumbnailURL": "http://cdn.helloproject.com/img/artist/m/0cec151a243d45d7aa10462af6896e7699f62aaf.jpg",
                "dateOfBirth": "2003-10-20T15:00:00Z",
                "bloodType": "B",
                "joinAt": "2018-11-22T15:00:00Z",
                "graduateAt": "2020-10-13T23:59:59Z"
              },
              {
                "id": "8589934615",
                "key": "layla_ise",
                "artistKey": "angerme",
                "name": "伊勢鈴蘭",
                "nameKana": "イセレイラ",
                "thumbnailURL": "http://cdn.helloproject.com/img/artist/m/d38d7e25ba05f84f2afe05642eb0ded6bcb8f47c.jpg",
                "dateOfBirth": "2004-01-18T15:00:00Z",
                "bloodType": "A",
                "joinAt": "2018-11-22T15:00:00Z",
                "graduateAt": null
              },
              {
                "id": "8589934616",
                "key": "rin_hashisako",
                "artistKey": "angerme",
                "name": "橋迫鈴",
                "nameKana": "ハシサコリン",
                "thumbnailURL": "http://cdn.helloproject.com/img/artist/m/cd2fdfb827d2e7cbb2838950122b431a058160bd.jpg",
                "dateOfBirth": "2005-10-05T15:00:00Z",
                "bloodType": "O",
                "joinAt": "2019-07-02T15:00:00Z",
                "graduateAt": null
              },
              {
                "id": "8589934660",
                "key": "rina_katsuta",
                "artistKey": "angerme",
                "name": "勝田里奈",
                "nameKana": "カツタリナ",
                "thumbnailURL": "https://www.entamealive.com/wp-content/uploads/2019/07/katsuta02.jpg",
                "dateOfBirth": "1998-04-05T15:00:00Z",
                "bloodType": "A",
                "joinAt": "2011-08-13T15:00:00Z",
                "graduateAt": "2019-09-24T15:00:00Z"
              },
              {
                "id": "8589934661",
                "key": "meimi_tamura",
                "artistKey": "angerme",
                "name": "田村芽実",
                "nameKana": "タムラメイミ",
                "thumbnailURL": "https://userdisk.webry.biglobe.ne.jp/004/977/34/N000/000/022/145061832838025154177.jpg",
                "dateOfBirth": "1998-10-29T15:00:00Z",
                "bloodType": "O",
                "joinAt": "2011-08-13T15:00:00Z",
                "graduateAt": "2016-05-29T15:00:00Z"
              },
              {
                "id": "8589934662",
                "key": "maho_aikata",
                "artistKey": "angerme",
                "name": "相川茉穂",
                "nameKana": "アイカワマホ",
                "thumbnailURL": "https://stat.ameba.jp/user_images/20170111/23/offside12/66/47/j/o0475055013843459962.jpg?caw=800",
                "dateOfBirth": "1999-03-25T15:00:00Z",
                "bloodType": "A",
                "joinAt": "2014-10-03T15:00:00Z",
                "graduateAt": "2017-12-30T15:00:00Z"
              },
              {
                "id": "8589934669",
                "key": "rin_kawana",
                "artistKey": "angerme",
                "name": "川名凜",
                "nameKana": "カワナリン",
                "thumbnailURL": "http://cdn.helloproject.com/img/artist/m/5a8d016a45bf9f2002bdde6930db55e3c386e289.jpg",
                "dateOfBirth": "2003-12-05T15:00:00Z",
                "bloodType": "B",
                "joinAt": "2020-11-01T15:00:00Z",
                "graduateAt": null
              },
              {
                "id": "8589934670",
                "key": "shion_tamenaga",
                "artistKey": "angerme",
                "name": "為永幸音",
                "nameKana": "タメナガシオン",
                "thumbnailURL": "http://cdn.helloproject.com/img/artist/m/6fb08bd80990f60f45a4a60ab8062257bb8c255c.jpg",
                "dateOfBirth": "2004-02-08T15:00:00Z",
                "bloodType": "O",
                "joinAt": "2020-11-01T15:00:00Z",
                "graduateAt": null
              },
              {
                "id": "8589934671",
                "key": "wakana_matsumoto",
                "artistKey": "angerme",
                "name": "松本わかな",
                "nameKana": "マツモトワカナ",
                "thumbnailURL": "http://cdn.helloproject.com/img/artist/m/232655eb4747f32898d78616a6a0e6e09e81ceca.jpg",
                "dateOfBirth": "2007-08-31T15:00:00Z",
                "bloodType": "AB",
                "joinAt": "2020-11-01T15:00:00Z",
                "graduateAt": null
              },
              {
                "id": "8590085285",
                "key": "yuki_hirayama",
                "artistKey": "angerme",
                "name": "平山遊季",
                "nameKana": "ヒラヤマユキ",
                "thumbnailURL": "http://cdn.helloproject.com/img/artist/m/8bb0cf2e05f15efbce27733b1daaccc0a69dd766.jpg",
                "dateOfBirth": "2006-07-24T15:00:00Z",
                "bloodType": "A",
                "joinAt": "2021-12-29T15:00:00Z",
                "graduateAt": null
              },
              {
                "id": "8590783732",
                "key": "yukiho_shimoitani",
                "artistKey": "angerme",
                "name": "下井谷幸穂",
                "nameKana": "シモイタニユキホ",
                "thumbnailURL": "http://cdn.helloproject.com/img/artist/m/236014f96812c7cebd5784f76a9a9b6cbb66c6a8.jpg",
                "dateOfBirth": "2006-08-03T15:00:00Z",
                "bloodType": "O",
                "joinAt": "2023-05-22T15:00:00Z",
                "graduateAt": null
              },
              {
                "id": "8590783733",
                "key": "hana_goto",
                "artistKey": "angerme",
                "name": "後藤花",
                "nameKana": "ゴトウハナ",
                "thumbnailURL": "http://cdn.helloproject.com/img/artist/m/1bf1584f6584f6379a1d9026ed9af275df5c0480.jpg",
                "dateOfBirth": "2008-06-04T15:00:00Z",
                "bloodType": "O",
                "joinAt": "2023-05-22T15:00:00Z",
                "graduateAt": null
              }
            ]
          },
          {
            "id": "3",
            "key": "juicejuice",
            "name": "Juice=Juice",
            "thumbnailURL": "http://cdn.helloproject.com/img/artist/m/f17cbeb1c69911f548b5ea8ab2be56c7a4eb668d.jpg",
            "members": [
              {
                "id": "8589934617",
                "key": "tomoko_kanazawa",
                "artistKey": "juicejuice",
                "name": "金澤朋子",
                "nameKana": "カナザワトモコ",
                "thumbnailURL": "http://cdn.helloproject.com/img/artist/m/392d8f9f5473df532be1ef0e20aa2d4555997b2b.jpg",
                "dateOfBirth": "1995-07-01T15:00:00Z",
                "bloodType": "B",
                "joinAt": "2013-02-24T15:00:00Z",
                "graduateAt": "2021-11-25T23:59:59Z"
              },
              {
                "id": "8589934618",
                "key": "sayuki_takagi",
                "artistKey": "juicejuice",
                "name": "高木紗友希",
                "nameKana": "タカギサユキ",
                "thumbnailURL": "http://cdn.helloproject.com/img/artist/m/58e11168849faa85bd5cb227e9c72d7f9d44865e.jpg",
                "dateOfBirth": "1997-04-20T15:00:00Z",
                "bloodType": "A",
                "joinAt": "2013-02-24T15:00:00Z",
                "graduateAt": "2021-02-12T23:59:59Z"
              },
              {
                "id": "8589934619",
                "key": "karin_miyamoto",
                "artistKey": "juicejuice",
                "name": "宮本佳林",
                "nameKana": "ミヤモトカリン",
                "thumbnailURL": "http://cdn.helloproject.com/img/artist/m/eed0cd62d68c3d48ed89bf18bdad6bf9e779f3a0.jpg",
                "dateOfBirth": "1998-11-30T15:00:00Z",
                "bloodType": "O",
                "joinAt": "2013-02-24T15:00:00Z",
                "graduateAt": "2020-12-11T23:59:59Z"
              },
              {
                "id": "8589934620",
                "key": "akari_uemura",
                "artistKey": "juicejuice",
                "name": "植村あかり",
                "nameKana": "ウエムラアカリ",
                "thumbnailURL": "http://cdn.helloproject.com/img/artist/m/365a21ba927880f37c74909ee3dfc2654034853e.jpg",
                "dateOfBirth": "1998-12-29T15:00:00Z",
                "bloodType": "O",
                "joinAt": "2013-02-24T15:00:00Z",
                "graduateAt": "2024-06-17T23:59:59Z"
              },
              {
                "id": "8589934621",
                "key": "ruru_dambara",
                "artistKey": "juicejuice",
                "name": "段原瑠々",
                "nameKana": "ダンバラルル",
                "thumbnailURL": "http://cdn.helloproject.com/img/artist/m/acff7e0af241a30011643aa303f1cbff9c064a3c.jpg",
                "dateOfBirth": "2001-05-06T15:00:00Z",
                "bloodType": "A",
                "joinAt": "2017-06-25T15:00:00Z",
                "graduateAt": null
              },
              {
                "id": "8589934622",
                "key": "manaka_inaba",
                "artistKey": "juicejuice",
                "name": "稲場愛香",
                "nameKana": "イナバマナカ",
                "thumbnailURL": "http://cdn.helloproject.com/img/artist/m/41e6b0ace5b82eadb5da6bedda1d29a5f353f18d.jpg",
                "dateOfBirth": "1997-12-26T15:00:00Z",
                "bloodType": "B",
                "joinAt": "2014-11-04T15:00:00Z",
                "graduateAt": "2022-05-31T23:59:59Z"
              },
              {
                "id": "8589934623",
                "key": "yume_kudou",
                "artistKey": "juicejuice",
                "name": "工藤由愛",
                "nameKana": "クドウユメ",
                "thumbnailURL": "http://cdn.helloproject.com/img/artist/m/9020babf1afe1101cd6c9e38843ff71ea3e20be8.jpg",
                "dateOfBirth": "2004-09-27T15:00:00Z",
                "bloodType": "A",
                "joinAt": "2019-06-13T15:00:00Z",
                "graduateAt": null
              },
              {
                "id": "8589934624",
                "key": "riai_matsunaga",
                "artistKey": "juicejuice",
                "name": "松永里愛",
                "nameKana": "マツナガリアイ",
                "thumbnailURL": "http://cdn.helloproject.com/img/artist/m/a069bb1f932be748008694204cbf0763049b2635.jpg",
                "dateOfBirth": "2005-07-06T15:00:00Z",
                "bloodType": "A",
                "joinAt": "2019-06-13T15:00:00Z",
                "graduateAt": null
              },
              {
                "id": "8589934666",
                "key": "yuka_miyazaki",
                "artistKey": "juicejuice",
                "name": "宮崎由加",
                "nameKana": "ミヤザキユカ",
                "thumbnailURL": "https://contents.oricon.co.jp/upimg/news/20181221/2126059_201812210640078001545393929c.jpg",
                "dateOfBirth": "1994-04-01T15:00:00Z",
                "bloodType": "O",
                "joinAt": "2013-02-24T15:00:00Z",
                "graduateAt": "2019-06-16T15:00:00Z"
              },
              {
                "id": "8589934667",
                "key": "yanagawa_nanami",
                "artistKey": "juicejuice",
                "name": "梁川奈々美",
                "nameKana": "ヤナガワナナミ",
                "thumbnailURL": "https://stat.ameba.jp/user_images/20181102/23/toshiki1970/76/bf/j/o0475055014295987031.jpg?caw=800",
                "dateOfBirth": "2002-01-05T15:00:00Z",
                "bloodType": "A",
                "joinAt": "2017-06-25T15:00:00Z",
                "graduateAt": "2019-03-10T15:00:00Z"
              },
              {
                "id": "8589934668",
                "key": "rei_inoue",
                "artistKey": "juicejuice",
                "name": "井上玲音",
                "nameKana": "イノウエレイ",
                "thumbnailURL": "http://cdn.helloproject.com/img/artist/m/2d08875bb8172ce45acd0cbcdc7f9bb14ad2652a.jpg",
                "dateOfBirth": "2001-07-16T15:00:00Z",
                "bloodType": "O",
                "joinAt": "2015-01-01T15:00:00Z",
                "graduateAt": null
              },
              {
                "id": "8589934672",
                "key": "ichika_arisawa",
                "artistKey": "juicejuice",
                "name": "有澤一華",
                "nameKana": "アリサワイチカ",
                "thumbnailURL": "http://cdn.helloproject.com/img/artist/m/5b0eaf840c393d9296635128921412a146a1a015.jpg",
                "dateOfBirth": "2003-12-22T15:00:00Z",
                "bloodType": "O",
                "joinAt": "2021-07-06T15:00:00Z",
                "graduateAt": null
              },
              {
                "id": "8589934673",
                "key": "risa_irie",
                "artistKey": "juicejuice",
                "name": "入江里咲",
                "nameKana": "イリエリサ",
                "thumbnailURL": "http://cdn.helloproject.com/img/artist/m/0ffb0d3959b77dd4c9bf96a6736fc34bb6a85ff7.jpg",
                "dateOfBirth": "2005-10-17T15:00:00Z",
                "bloodType": "A",
                "joinAt": "2021-07-06T15:00:00Z",
                "graduateAt": null
              },
              {
                "id": "8589934674",
                "key": "kisaki_ebata",
                "artistKey": "juicejuice",
                "name": "江端妃咲",
                "nameKana": "エバタキサキ",
                "thumbnailURL": "http://cdn.helloproject.com/img/artist/m/bb75f62a9ff5473eaba71bf69069ec116d268a4a.jpg",
                "dateOfBirth": "2007-01-29T15:00:00Z",
                "bloodType": "A",
                "joinAt": "2021-07-06T15:00:00Z",
                "graduateAt": null
              },
              {
                "id": "8590222529",
                "key": "sakura_ishiyama",
                "artistKey": "juicejuice",
                "name": "石山咲良",
                "nameKana": "イシヤマサクラ",
                "thumbnailURL": "http://cdn.helloproject.com/img/artist/m/7ea0ac7a56efac310beb619216ac1165db31c9fc.jpg",
                "dateOfBirth": "2004-02-21T15:00:00Z",
                "bloodType": "B",
                "joinAt": "2022-06-28T15:00:00Z",
                "graduateAt": null
              },
              {
                "id": "8590222530",
                "key": "akari_endo",
                "artistKey": "juicejuice",
                "name": "遠藤彩加里",
                "nameKana": "エンドウアカリ",
                "thumbnailURL": "http://cdn.helloproject.com/img/artist/m/96918635cd1540932e5ceb3727db4ffb5cf498fe.jpg",
                "dateOfBirth": "2008-04-25T15:00:00Z",
                "bloodType": "A",
                "joinAt": "2022-06-28T15:00:00Z",
                "graduateAt": null
              },
              {
                "id": "8590783744",
                "key": "mifu_kawashima",
                "artistKey": "juicejuice",
                "name": "川嶋美楓",
                "nameKana": "カワシマミフ",
                "thumbnailURL": "http://cdn.helloproject.com/img/artist/m/b73339df75264e1455c3cd9b780bf3a96628f57f.jpg",
                "dateOfBirth": "2007-12-12T15:00:00Z",
                "bloodType": "AB",
                "joinAt": "2023-05-22T15:00:00Z",
                "graduateAt": null
              }
            ]
          },
          {
            "id": "4",
            "key": "countrygirls",
            "name": "カントリー・ガールズ",
            "thumbnailURL": "http://cdn.helloproject.com/img/artist/m/0de545fd02bc79b8faab45327f67441005f42560.jpg",
            "members": [
              {
                "id": "8589934625",
                "key": "risa_yamaki",
                "artistKey": "countrygirls",
                "name": "山木梨沙",
                "nameKana": "ヤマキリサ",
                "thumbnailURL": "http://cdn.helloproject.com/img/artist/m/628b04c01fd268f619a6e2ee0f6976adb78f91c3.jpg",
                "dateOfBirth": "1997-10-13T15:00:00Z",
                "bloodType": "B",
                "joinAt": "2014-11-04T15:00:00Z",
                "graduateAt": "2019-12-25T15:00:00Z"
              },
              {
                "id": "8589934626",
                "key": "chisaki_morito",
                "artistKey": "countrygirls",
                "name": "森戸知沙希",
                "nameKana": "モリトチサキ",
                "thumbnailURL": "http://cdn.helloproject.com/img/artist/m/95d6b25afc64ce119df6605f721bddc982fc678d.jpg",
                "dateOfBirth": "2000-02-18T15:00:00Z",
                "bloodType": "A",
                "joinAt": "2014-11-04T15:00:00Z",
                "graduateAt": "2019-12-25T15:00:00Z"
              },
              {
                "id": "8589934627",
                "key": "mai_ozeki",
                "artistKey": "countrygirls",
                "name": "小関舞",
                "nameKana": "オゼキマイ",
                "thumbnailURL": "http://cdn.helloproject.com/img/artist/m/adaa01b151a1921a6a696aabdd5ac68f15a3b3a7.jpg",
                "dateOfBirth": "2002-02-09T15:00:00Z",
                "bloodType": "O",
                "joinAt": "2014-11-04T15:00:00Z",
                "graduateAt": "2019-12-25T15:00:00Z"
              },
              {
                "id": "8589934628",
                "key": "musubu_funaki",
                "artistKey": "countrygirls",
                "name": "船木結",
                "nameKana": "フナキムスブ",
                "thumbnailURL": "http://cdn.helloproject.com/img/artist/m/7aa4a4c45fdd31ae08cc667e718be612c6d9345c.jpg",
                "dateOfBirth": "2002-05-09T15:00:00Z",
                "bloodType": "O",
                "joinAt": "2015-11-04T15:00:00Z",
                "graduateAt": "2019-12-25T15:00:00Z"
              },
              {
                "id": "8589934663",
                "key": "nanami_yanagawa",
                "artistKey": "countrygirls",
                "name": "梁川奈々美",
                "nameKana": "ヤナガワナナミ",
                "thumbnailURL": "https://image.space.rakuten.co.jp/d/strg/ctrl/9/2a66680441a6600c737dedd30fbfe486e9d674bd.75.2.9.2.jpeg",
                "dateOfBirth": "2002-01-05T15:00:00Z",
                "bloodType": "A",
                "joinAt": "2015-11-04T15:00:00Z",
                "graduateAt": "2019-03-10T15:00:00Z"
              },
              {
                "id": "8589934664",
                "key": "manaka_inaba_c",
                "artistKey": "countrygirls",
                "name": "稲場愛香",
                "nameKana": "イナバマナカ",
                "thumbnailURL": "https://cdn-ak.f.st-hatena.com/images/fotolife/p/polka8dot/20160805/20160805204817.jpg",
                "dateOfBirth": "1997-12-26T15:00:00Z",
                "bloodType": "B",
                "joinAt": "2014-11-04T15:00:00Z",
                "graduateAt": "2016-08-03T15:00:00Z"
              },
              {
                "id": "8589934665",
                "key": "momoko_tsugunaga_c",
                "artistKey": "countrygirls",
                "name": "嗣永桃子",
                "nameKana": "ツグナガモモコ",
                "thumbnailURL": "https://stat.ameba.jp/user_images/20160420/21/hellopworld/cf/bb/j/o0475055013625033137.jpg?caw=800",
                "dateOfBirth": "1992-03-05T15:00:00Z",
                "bloodType": "O",
                "joinAt": "2014-11-04T15:00:00Z",
                "graduateAt": "2017-06-29T15:00:00Z"
              }
            ]
          },
          {
            "id": "5",
            "key": "kobushifactory",
            "name": "こぶしファクトリー",
            "thumbnailURL": "http://cdn.helloproject.com/img/artist/m/95d6977f58483a8586c28d9b86a40dfa57f23512.jpg",
            "members": [
              {
                "id": "8589934629",
                "key": "ayaka_hirose",
                "artistKey": "kobushifactory",
                "name": "広瀬彩海",
                "nameKana": "ヒロセアヤカ",
                "thumbnailURL": "http://cdn.helloproject.com/img/artist/m/8e3884aa8fb84bd357ea7b7556735fb90752bb3a.jpg",
                "dateOfBirth": "1999-08-03T15:00:00Z",
                "bloodType": "O",
                "joinAt": "2015-01-01T15:00:00Z",
                "graduateAt": "2020-03-30T23:59:59Z"
              },
              {
                "id": "8589934630",
                "key": "minami_nomura",
                "artistKey": "kobushifactory",
                "name": "野村みな美",
                "nameKana": "ノムラミナミ",
                "thumbnailURL": "http://cdn.helloproject.com/img/artist/m/c940265d065dd710f1eb13fc606b0d6c075a4183.jpg",
                "dateOfBirth": "2000-02-09T15:00:00Z",
                "bloodType": "B",
                "joinAt": "2015-01-01T15:00:00Z",
                "graduateAt": "2020-03-30T23:59:59Z"
              },
              {
                "id": "8589934631",
                "key": "ayano_hamaura",
                "artistKey": "kobushifactory",
                "name": "浜浦彩乃",
                "nameKana": "ハマウラアヤノ",
                "thumbnailURL": "http://cdn.helloproject.com/img/artist/m/7677a797a4f95557bb8cb526919f3d8ebe8b518d.jpg",
                "dateOfBirth": "2000-04-25T15:00:00Z",
                "bloodType": "AB",
                "joinAt": "2015-01-01T15:00:00Z",
                "graduateAt": "2020-03-30T23:59:59Z"
              },
              {
                "id": "8589934632",
                "key": "sakurako_wada",
                "artistKey": "kobushifactory",
                "name": "和田桜子",
                "nameKana": "ワダサクラコ",
                "thumbnailURL": "http://cdn.helloproject.com/img/artist/m/f2ca8febac34e3061e37fada823fb6401b72ef62.jpg",
                "dateOfBirth": "2001-03-07T15:00:00Z",
                "bloodType": "Ｂ",
                "joinAt": "2015-01-01T15:00:00Z",
                "graduateAt": "2020-03-30T23:59:59Z"
              },
              {
                "id": "8589934633",
                "key": "rei_inoue_k",
                "artistKey": "kobushifactory",
                "name": "井上玲音",
                "nameKana": "イノウエレイ",
                "thumbnailURL": "http://cdn.helloproject.com/img/artist/m/c00f2a4ba8cf161313b1dfb1f0126e12f2101c52.jpg",
                "dateOfBirth": "2001-07-16T15:00:00Z",
                "bloodType": "O",
                "joinAt": "2015-01-01T15:00:00Z",
                "graduateAt": "2020-03-30T23:59:59Z"
              },
              {
                "id": "8590637495",
                "key": "natsumi_taguchi",
                "artistKey": "kobushifactory",
                "name": "田口夏実",
                "nameKana": "タグチナツミ",
                "thumbnailURL": "https://raw.githubusercontent.com/emolga587/hpsort2/master/public/member_pics/%E7%94%B0%E5%8F%A3%E5%A4%8F%E5%AE%9F.jpg",
                "dateOfBirth": "2000-07-20T15:00:00Z",
                "bloodType": "A",
                "joinAt": "2014-12-31T15:00:00Z",
                "graduateAt": "2017-12-06T14:59:59Z"
              },
              {
                "id": "8590637496",
                "key": "rio_fujii",
                "artistKey": "kobushifactory",
                "name": "藤井梨央",
                "nameKana": "フジイリオ",
                "thumbnailURL": "https://raw.githubusercontent.com/emolga587/hpsort2/master/public/member_pics/%E8%97%A4%E4%BA%95%E6%A2%A8%E5%A4%AE.jpg",
                "dateOfBirth": "1999-03-03T15:00:00Z",
                "bloodType": "B",
                "joinAt": "2014-12-31T15:00:00Z",
                "graduateAt": "2017-09-06T14:59:59Z"
              },
              {
                "id": "8590637497",
                "key": "rena_ogawa",
                "artistKey": "kobushifactory",
                "name": "小川麗奈",
                "nameKana": "小川麗奈",
                "thumbnailURL": "https://raw.githubusercontent.com/emolga587/hpsort2/master/public/member_pics/%E5%B0%8F%E5%B7%9D%E9%BA%97%E5%A5%88.jpg",
                "dateOfBirth": "2000-03-26T15:00:00Z",
                "bloodType": "A",
                "joinAt": "2014-12-31T15:00:00Z",
                "graduateAt": "2020-09-06T14:59:59Z"
              }
            ]
          },
          {
            "id": "6",
            "key": "tsubakifactory",
            "name": "つばきファクトリー",
            "thumbnailURL": "http://cdn.helloproject.com/img/artist/m/46d5b6b4940afd9e73a38433588e59dbadbe50ec.jpg",
            "members": [
              {
                "id": "8589934634",
                "key": "riko_yamagishi",
                "artistKey": "tsubakifactory",
                "name": "山岸理子",
                "nameKana": "ヤマギシリコ",
                "thumbnailURL": "http://cdn.helloproject.com/img/artist/m/94077777418909fcc34f57e994d798870c695bc8.jpg",
                "dateOfBirth": "1998-11-23T15:00:00Z",
                "bloodType": "B",
                "joinAt": "2015-04-28T15:00:00Z",
                "graduateAt": "2023-11-07T23:59:59Z"
              },
              {
                "id": "8589934635",
                "key": "risa_ogata",
                "artistKey": "tsubakifactory",
                "name": "小片リサ",
                "nameKana": "オガタリサ",
                "thumbnailURL": "http://cdn.helloproject.com/img/artist/m/4eaa066845403b6cd5006ccca7a8526618c2d18d.jpg",
                "dateOfBirth": "1998-11-04T15:00:00Z",
                "bloodType": "A",
                "joinAt": "2015-04-28T15:00:00Z",
                "graduateAt": "2020-12-28T23:59:59Z"
              },
              {
                "id": "8589934636",
                "key": "kisora_niinuma",
                "artistKey": "tsubakifactory",
                "name": "新沼希空",
                "nameKana": "ニイヌマキソラ",
                "thumbnailURL": "http://cdn.helloproject.com/img/artist/m/1a332fd76a054f1660bb7cd12a229b526be9b4f6.jpg",
                "dateOfBirth": "1999-10-19T15:00:00Z",
                "bloodType": "O",
                "joinAt": "2015-04-28T15:00:00Z",
                "graduateAt": "2024-06-11T23:59:59Z"
              },
              {
                "id": "8589934637",
                "key": "ami_tanimoto",
                "artistKey": "tsubakifactory",
                "name": "谷本安美",
                "nameKana": "タニモトアミ",
                "thumbnailURL": "http://cdn.helloproject.com/img/artist/m/58e301392ec9b7fbf0bfce9f6074718550054895.jpg",
                "dateOfBirth": "1999-11-15T15:00:00Z",
                "bloodType": "B",
                "joinAt": "2015-04-28T15:00:00Z",
                "graduateAt": null
              },
              {
                "id": "8589934638",
                "key": "yumeno_kishimoto",
                "artistKey": "tsubakifactory",
                "name": "岸本ゆめの",
                "nameKana": "キシモトユメノ",
                "thumbnailURL": "http://cdn.helloproject.com/img/artist/m/e0931aa33a6da3118044cd491ab182c4fa00d2c6.jpg",
                "dateOfBirth": "2000-03-31T15:00:00Z",
                "bloodType": "B",
                "joinAt": "2015-04-28T15:00:00Z",
                "graduateAt": "2023-11-07T23:59:59Z"
              },
              {
                "id": "8589934639",
                "key": "kiki_asakura",
                "artistKey": "tsubakifactory",
                "name": "浅倉樹々",
                "nameKana": "アサクラキキ",
                "thumbnailURL": "http://cdn.helloproject.com/img/artist/m/4a54d3dffc03626f86e6dab1578951712f494965.jpg",
                "dateOfBirth": "2000-09-02T15:00:00Z",
                "bloodType": "AB",
                "joinAt": "2015-04-28T15:00:00Z",
                "graduateAt": "2023-04-03T23:59:59Z"
              },
              {
                "id": "8589934640",
                "key": "mizuho_ono",
                "artistKey": "tsubakifactory",
                "name": "小野瑞歩",
                "nameKana": "オノミズホ",
                "thumbnailURL": "http://cdn.helloproject.com/img/artist/m/485942d08d22032e5f82d8a1ed1443c9bf6556af.jpg",
                "dateOfBirth": "2000-09-28T15:00:00Z",
                "bloodType": "O",
                "joinAt": "2016-08-12T15:00:00Z",
                "graduateAt": null
              },
              {
                "id": "8589934641",
                "key": "saori_onoda",
                "artistKey": "tsubakifactory",
                "name": "小野田紗栞",
                "nameKana": "オノダサオリ",
                "thumbnailURL": "http://cdn.helloproject.com/img/artist/m/94a01bfa58059defbad5085e7ce11726fc2b236a.jpg",
                "dateOfBirth": "2001-12-16T15:00:00Z",
                "bloodType": "O",
                "joinAt": "2016-08-12T15:00:00Z",
                "graduateAt": null
              },
              {
                "id": "8589934642",
                "key": "mao_akiyama",
                "artistKey": "tsubakifactory",
                "name": "秋山眞緒",
                "nameKana": "アキヤママオ",
                "thumbnailURL": "http://cdn.helloproject.com/img/artist/m/eb9d5940053aae3aa116a1c4f87bcc9d7c4a1fac.jpg",
                "dateOfBirth": "2002-07-28T15:00:00Z",
                "bloodType": "B",
                "joinAt": "2016-08-12T15:00:00Z",
                "graduateAt": null
              },
              {
                "id": "8589934675",
                "key": "yuumi_kasai",
                "artistKey": "tsubakifactory",
                "name": "河西結心",
                "nameKana": "カサイユウミ",
                "thumbnailURL": "http://cdn.helloproject.com/img/artist/m/1e1dbcba1b58264828592b9a88faa31a8d6b6a4e.jpg",
                "dateOfBirth": "2003-07-29T15:00:00Z",
                "bloodType": "O",
                "joinAt": "2021-07-06T15:00:00Z",
                "graduateAt": null
              },
              {
                "id": "8589934676",
                "key": "shiori_yagi",
                "artistKey": "tsubakifactory",
                "name": "八木栞",
                "nameKana": "ヤギシオリ",
                "thumbnailURL": "http://cdn.helloproject.com/img/artist/m/51aad55a341951f36456ffce740daf7e880ce580.jpg",
                "dateOfBirth": "2003-09-18T15:00:00Z",
                "bloodType": "O",
                "joinAt": "2021-07-06T15:00:00Z",
                "graduateAt": null
              },
              {
                "id": "8589934677",
                "key": "marine_fukuda",
                "artistKey": "tsubakifactory",
                "name": "福田真琳",
                "nameKana": "フクダマリン",
                "thumbnailURL": "http://cdn.helloproject.com/img/artist/m/3842f82215f95b4f2715bb941703a3bcf7f9affe.jpg",
                "dateOfBirth": "2004-10-17T15:00:00Z",
                "bloodType": "AB",
                "joinAt": "2021-07-06T15:00:00Z",
                "graduateAt": null
              },
              {
                "id": "8589934678",
                "key": "runo_yofu",
                "artistKey": "tsubakifactory",
                "name": "豫風瑠乃",
                "nameKana": "ヨフウルノ",
                "thumbnailURL": "http://cdn.helloproject.com/img/artist/m/ddb8a14330495de4bcc4ee41fc7b848076867f03.jpg",
                "dateOfBirth": "2007-12-19T15:00:00Z",
                "bloodType": "O",
                "joinAt": "2021-07-06T15:00:00Z",
                "graduateAt": null
              },
              {
                "id": "8590919624",
                "key": "mihane_ishii",
                "artistKey": "tsubakifactory",
                "name": "石井泉羽",
                "nameKana": "イシイミハネ",
                "thumbnailURL": "http://cdn.helloproject.com/img/artist/m/2b7651885b39a510579977947b713c64edeca635.jpg",
                "dateOfBirth": "2008-10-19T15:00:00Z",
                "bloodType": "O",
                "joinAt": "2024-02-06T15:00:00Z",
                "graduateAt": null
              },
              {
                "id": "8590919625",
                "key": "yuu_murata",
                "artistKey": "tsubakifactory",
                "name": "村田結生",
                "nameKana": "ムラタユウ",
                "thumbnailURL": "http://cdn.helloproject.com/img/artist/m/6daf325ad271eb4522fe7594458216e49c47f862.jpg",
                "dateOfBirth": "2010-03-11T15:00:00Z",
                "bloodType": "O",
                "joinAt": "2024-02-06T15:00:00Z",
                "graduateAt": null
              },
              {
                "id": "8590919626",
                "key": "fuka_doi",
                "artistKey": "tsubakifactory",
                "name": "土居楓奏",
                "nameKana": "ドイフウカ",
                "thumbnailURL": "http://cdn.helloproject.com/img/artist/m/6325924874d1c117e3c5ec1a023793e45e61e0a8.jpg",
                "dateOfBirth": "2010-03-22T15:00:00Z",
                "bloodType": "AB",
                "joinAt": "2024-02-06T15:00:00Z",
                "graduateAt": null
              }
            ]
          },
          {
            "id": "7",
            "key": "beyooooonds",
            "name": "BEYOOOOONDS",
            "thumbnailURL": "http://cdn.helloproject.com/img/artist/m/30adc3f6da04a981e837496342fe67368ab43ac0.jpg",
            "members": [
              {
                "id": "8589934643",
                "key": "reina_ichioka",
                "artistKey": "beyooooonds",
                "name": "一岡伶奈",
                "nameKana": "イチオカレイナ",
                "thumbnailURL": "http://cdn.helloproject.com/img/artist/m/ae8afdc41ee4f100f2acbdc646d81a9f64fec1fa.jpg",
                "dateOfBirth": "1999-02-24T15:00:00Z",
                "bloodType": "A",
                "joinAt": "2017-05-04T15:00:00Z",
                "graduateAt": "2024-03-01T23:59:59Z"
              },
              {
                "id": "8589934644",
                "key": "rika_shimakura",
                "artistKey": "beyooooonds",
                "name": "島倉りか",
                "nameKana": "シマクラリカ",
                "thumbnailURL": "http://cdn.helloproject.com/img/artist/m/d51b764876b32839be6b40391bda069ae6e4292a.jpg",
                "dateOfBirth": "2000-08-19T15:00:00Z",
                "bloodType": "A",
                "joinAt": "2018-06-08T15:00:00Z",
                "graduateAt": null
              },
              {
                "id": "8589934645",
                "key": "shiori_nishida",
                "artistKey": "beyooooonds",
                "name": "西田汐里",
                "nameKana": "ニシダシオリ",
                "thumbnailURL": "http://cdn.helloproject.com/img/artist/m/f08fcb038840880ee48a9d54048b74a8c57e67d8.jpg",
                "dateOfBirth": "2003-06-06T15:00:00Z",
                "bloodType": "B",
                "joinAt": "2018-06-08T15:00:00Z",
                "graduateAt": null
              },
              {
                "id": "8589934646",
                "key": "saya_eguchi",
                "artistKey": "beyooooonds",
                "name": "江口紗耶",
                "nameKana": "エグチサヤ",
                "thumbnailURL": "http://cdn.helloproject.com/img/artist/m/713a89446b9e7c8c70e7052dea15fc9220448afe.jpg",
                "dateOfBirth": "2003-07-31T15:00:00Z",
                "bloodType": "O",
                "joinAt": "2018-06-08T15:00:00Z",
                "graduateAt": null
              },
              {
                "id": "8589934647",
                "key": "kurumi_takase",
                "artistKey": "beyooooonds",
                "name": "高瀬くるみ",
                "nameKana": "タカセクルミ",
                "thumbnailURL": "http://cdn.helloproject.com/img/artist/m/756e287737fd796e41a94bfa52d3ce0caea2c387.jpg",
                "dateOfBirth": "1999-03-15T15:00:00Z",
                "bloodType": "A",
                "joinAt": "2017-05-04T15:00:00Z",
                "graduateAt": null
              },
              {
                "id": "8589934648",
                "key": "kokoro_maeda",
                "artistKey": "beyooooonds",
                "name": "前田こころ",
                "nameKana": "マエダココロ",
                "thumbnailURL": "http://cdn.helloproject.com/img/artist/m/3e7fac472ba63937df143d2d1461028a2d33595a.jpg",
                "dateOfBirth": "2002-06-22T15:00:00Z",
                "bloodType": "A",
                "joinAt": "2018-06-08T15:00:00Z",
                "graduateAt": null
              },
              {
                "id": "8589934649",
                "key": "yuhane_yamazaki",
                "artistKey": "beyooooonds",
                "name": "山﨑夢羽",
                "nameKana": "ヤマザキユハネ",
                "thumbnailURL": "http://cdn.helloproject.com/img/artist/m/eb4c87bc0729f5ca99bc6333b34719939197d4ca.jpg",
                "dateOfBirth": "2002-11-04T15:00:00Z",
                "bloodType": "AB",
                "joinAt": "2018-06-08T15:00:00Z",
                "graduateAt": "2024-06-28T23:59:59Z"
              },
              {
                "id": "8589934650",
                "key": "minami_okamura",
                "artistKey": "beyooooonds",
                "name": "岡村美波",
                "nameKana": "オカムラミナミ",
                "thumbnailURL": "http://cdn.helloproject.com/img/artist/m/d7bb8f85f6a3c99c7028d8cf8e220e4facdd17d4.jpg",
                "dateOfBirth": "2004-10-19T15:00:00Z",
                "bloodType": "O",
                "joinAt": "2018-06-08T15:00:00Z",
                "graduateAt": null
              },
              {
                "id": "8589934651",
                "key": "momohime_kiyono",
                "artistKey": "beyooooonds",
                "name": "清野桃々姫",
                "nameKana": "キヨノモモヒメ",
                "thumbnailURL": "http://cdn.helloproject.com/img/artist/m/bfa2a43d378bd78d2bc2f4b93daa1e9cea57cb62.jpg",
                "dateOfBirth": "2004-12-21T15:00:00Z",
                "bloodType": "A",
                "joinAt": "2017-05-04T15:00:00Z",
                "graduateAt": null
              },
              {
                "id": "8589934652",
                "key": "miyo_hirai",
                "artistKey": "beyooooonds",
                "name": "平井美葉",
                "nameKana": "ヒライミヨ",
                "thumbnailURL": "http://cdn.helloproject.com/img/artist/m/7f180abc696dce0dab77b20f89fbd1c44cf62b27.jpg",
                "dateOfBirth": "1999-12-10T15:00:00Z",
                "bloodType": "A",
                "joinAt": "2018-12-02T15:00:00Z",
                "graduateAt": null
              },
              {
                "id": "8589934653",
                "key": "honoka_kobayashi",
                "artistKey": "beyooooonds",
                "name": "小林萌花",
                "nameKana": "コバヤシホノカ",
                "thumbnailURL": "http://cdn.helloproject.com/img/artist/m/15d1201821ec95a72f11e893ad5ca263fbae9a4f.jpg",
                "dateOfBirth": "2000-08-15T15:00:00Z",
                "bloodType": "A",
                "joinAt": "2018-12-02T15:00:00Z",
                "graduateAt": null
              },
              {
                "id": "8589934654",
                "key": "utano_satoyoshi",
                "artistKey": "beyooooonds",
                "name": "里吉うたの",
                "nameKana": "サトヨシウタノ",
                "thumbnailURL": "http://cdn.helloproject.com/img/artist/m/43088e4f133e5df6392914720327292523b41b38.jpg",
                "dateOfBirth": "2000-09-21T15:00:00Z",
                "bloodType": "A",
                "joinAt": "2018-12-02T15:00:00Z",
                "graduateAt": null
              }
            ]
          },
          {
            "id": "8",
            "key": "ochanorma",
            "name": "OCHA NORMA",
            "thumbnailURL": "http://cdn.helloproject.com/img/artist/m/b936adf6e859cbb438cb0c05e100a5816ea916dc.jpg",
            "members": [
              {
                "id": "8590061983",
                "key": "madoka_saito",
                "artistKey": "ochanorma",
                "name": "斉藤円香",
                "nameKana": "サイトウマドカ",
                "thumbnailURL": "http://cdn.helloproject.com/img/artist/m/c54c24dd48173eea83726da8eecbe4bdb6258876.jpg",
                "dateOfBirth": "2002-10-27T15:00:00Z",
                "bloodType": "O",
                "joinAt": "2021-12-11T15:00:00Z",
                "graduateAt": null
              },
              {
                "id": "8590061984",
                "key": "ruli_hiromoto",
                "artistKey": "ochanorma",
                "name": "広本瑠璃",
                "nameKana": "ヒロモトルリ",
                "thumbnailURL": "http://cdn.helloproject.com/img/artist/m/6b94d034092a13654187d05f06a0c77ba5b0cd6a.jpg",
                "dateOfBirth": "2003-06-17T15:00:00Z",
                "bloodType": "B",
                "joinAt": "2021-12-11T15:00:00Z",
                "graduateAt": null
              },
              {
                "id": "8590061985",
                "key": "kanami_ishiguri",
                "artistKey": "ochanorma",
                "name": "石栗奏美",
                "nameKana": "イシグリカナミ",
                "thumbnailURL": "http://cdn.helloproject.com/img/artist/m/aa2447abee917a8ffc5cfca00592708c6f6e823a.jpg",
                "dateOfBirth": "2004-04-19T15:00:00Z",
                "bloodType": "A",
                "joinAt": "2021-12-11T15:00:00Z",
                "graduateAt": null
              },
              {
                "id": "8590061986",
                "key": "kirara_yonemura",
                "artistKey": "ochanorma",
                "name": "米村姫良々",
                "nameKana": "ヨネムラキララ",
                "thumbnailURL": "http://cdn.helloproject.com/img/artist/m/f41285e8adf15d1a38d24ddd03ee432db776804e.jpg",
                "dateOfBirth": "2004-04-29T15:00:00Z",
                "bloodType": "A",
                "joinAt": "2021-12-11T15:00:00Z",
                "graduateAt": null
              },
              {
                "id": "8590061987",
                "key": "nanami_kubota",
                "artistKey": "ochanorma",
                "name": "窪田七海",
                "nameKana": "クボタナナミ",
                "thumbnailURL": "http://cdn.helloproject.com/img/artist/m/f70849966386361884f40c65eaa3345c716c4b1d.jpg",
                "dateOfBirth": "2004-07-22T15:00:00Z",
                "bloodType": "A",
                "joinAt": "2021-12-11T15:00:00Z",
                "graduateAt": null
              },
              {
                "id": "8590061988",
                "key": "sumire_tashiro",
                "artistKey": "ochanorma",
                "name": "田代すみれ",
                "nameKana": "タシロスミレ",
                "thumbnailURL": "http://cdn.helloproject.com/img/artist/m/bc0850d34cdc038e2746630483e14627eb5d0b32.jpg",
                "dateOfBirth": "2005-06-15T15:00:00Z",
                "bloodType": "不明",
                "joinAt": "2021-12-11T15:00:00Z",
                "graduateAt": null
              },
              {
                "id": "8590061989",
                "key": "natsume_nakayama",
                "artistKey": "ochanorma",
                "name": "中山夏月姫",
                "nameKana": "ナカヤマナツメ",
                "thumbnailURL": "http://cdn.helloproject.com/img/artist/m/a76ec6ace01ba99bac7fbf71e676ea7a0c0d80c8.jpg",
                "dateOfBirth": "2005-07-19T15:00:00Z",
                "bloodType": "A",
                "joinAt": "2021-12-11T15:00:00Z",
                "graduateAt": null
              },
              {
                "id": "8590061990",
                "key": "miku_nishizaki",
                "artistKey": "ochanorma",
                "name": "西﨑美空",
                "nameKana": "ニシザキミク",
                "thumbnailURL": "http://cdn.helloproject.com/img/artist/m/e23c4da7cb3d937830d352dc507645a758c4c023.jpg",
                "dateOfBirth": "2006-04-16T15:00:00Z",
                "bloodType": "O",
                "joinAt": "2021-12-11T15:00:00Z",
                "graduateAt": null
              },
              {
                "id": "8590061991",
                "key": "momo_kitahara",
                "artistKey": "ochanorma",
                "name": "北原もも",
                "nameKana": "キタハラモモ",
                "thumbnailURL": "http://cdn.helloproject.com/img/artist/m/eecf5ce43b96ff42cbed72ff423e058159ed70c9.jpg",
                "dateOfBirth": "2006-08-29T15:00:00Z",
                "bloodType": "A",
                "joinAt": "2021-12-11T15:00:00Z",
                "graduateAt": null
              },
              {
                "id": "8590061992",
                "key": "roko_tsutsui",
                "artistKey": "ochanorma",
                "name": "筒井澪心",
                "nameKana": "ツツイロコ",
                "thumbnailURL": "http://cdn.helloproject.com/img/artist/m/b9b705b4f03c44924c0259cf55a1fc2e8974dba3.jpg",
                "dateOfBirth": "2007-08-09T15:00:00Z",
                "bloodType": "A",
                "joinAt": "2021-12-11T15:00:00Z",
                "graduateAt": null
              }
            ]
          }
        ],
        "id": "helloproject"
      },
      "me": {
        "id": "42949672973",
        "username": "yssk22",
        "clientId": "anonymous",
        "clientName": "anonymous",
        "followings": [
          {
            "type": "follow_with_notification",
            "member": {
              "id": "8589934592"
            },
            "id": "55834574890"
          },
          {
            "type": "unfollow",
            "member": {
              "id": "8589934593"
            },
            "id": "55834574891"
          },
          {
            "type": "unfollow",
            "member": {
              "id": "8589934594"
            },
            "id": "55834574888"
          },
          {
            "type": "follow_with_notification",
            "member": {
              "id": "8589934596"
            },
            "id": "55834574885"
          },
          {
            "type": "unfollow",
            "member": {
              "id": "8589934597"
            },
            "id": "55834574880"
          },
          {
            "type": "follow_with_notification",
            "member": {
              "id": "8589934601"
            },
            "id": "55834574884"
          },
          {
            "type": "unfollow",
            "member": {
              "id": "8589934603"
            },
            "id": "55834574882"
          },
          {
            "type": "unfollow",
            "member": {
              "id": "8589934604"
            },
            "id": "55834574889"
          },
          {
            "type": "follow_with_notification",
            "member": {
              "id": "8589934605"
            },
            "id": "55834574881"
          },
          {
            "type": "unfollow",
            "member": {
              "id": "8589934611"
            },
            "id": "55834574887"
          },
          {
            "type": "unfollow",
            "member": {
              "id": "8589934615"
            },
            "id": "55834574916"
          },
          {
            "type": "follow_with_notification",
            "member": {
              "id": "8589934621"
            },
            "id": "55834574908"
          },
          {
            "type": "follow",
            "member": {
              "id": "8589934623"
            },
            "id": "55834576108"
          },
          {
            "type": "follow",
            "member": {
              "id": "8589934624"
            },
            "id": "55834574917"
          },
          {
            "type": "unfollow",
            "member": {
              "id": "8589934640"
            },
            "id": "55834575067"
          },
          {
            "type": "follow",
            "member": {
              "id": "8589934644"
            },
            "id": "55834574918"
          },
          {
            "type": "unfollow",
            "member": {
              "id": "8589934649"
            },
            "id": "55834574883"
          },
          {
            "type": "unfollow",
            "member": {
              "id": "8589934653"
            },
            "id": "55834574886"
          },
          {
            "type": "follow",
            "member": {
              "id": "8589934672"
            },
            "id": "55834576081"
          },
          {
            "type": "follow_with_notification",
            "member": {
              "id": "8589934673"
            },
            "id": "55834575266"
          },
          {
            "type": "follow_with_notification",
            "member": {
              "id": "8589934674"
            },
            "id": "55834575468"
          },
          {
            "type": "unfollow",
            "member": {
              "id": "8589934676"
            },
            "id": "55834582384"
          },
          {
            "type": "follow",
            "member": {
              "id": "8590222529"
            },
            "id": "55834576327"
          },
          {
            "type": "follow",
            "member": {
              "id": "8590222530"
            },
            "id": "55834576328"
          },
          {
            "type": "follow_with_notification",
            "member": {
              "id": "8590783732"
            },
            "id": "55834583639"
          },
          {
            "type": "follow",
            "member": {
              "id": "8590783744"
            },
            "id": "55834583569"
          },
          {
            "type": "follow_with_notification",
            "member": {
              "id": "8590786239"
            },
            "id": "55834583346"
          }
        ],
        "sortHistories": {
          "edges": [
            {
              "node": {
                "id": "51539607743",
                "createdAt": "2024-06-15T02:48:56Z",
                "sortResult": {
                  "records": [
                    {
                      "artistId": 3,
                      "memberId": 8589934673,
                      "memberKey": "risa_irie"
                    },
                    {
                      "artistId": 3,
                      "memberId": 8589934674,
                      "memberKey": "kisaki_ebata"
                    },
                    {
                      "artistId": 3,
                      "memberId": 8589934624,
                      "memberKey": "riai_matsunaga"
                    },
                    {
                      "artistId": 3,
                      "memberId": 8589934623,
                      "memberKey": "yume_kudou"
                    },
                    {
                      "artistId": 3,
                      "memberId": 8590222530,
                      "memberKey": "akari_endo"
                    },
                    {
                      "artistId": 3,
                      "memberId": 8589934672,
                      "memberKey": "ichika_arisawa"
                    },
                    {
                      "artistId": 3,
                      "memberId": 8590222529,
                      "memberKey": "sakura_ishiyama"
                    },
                    {
                      "artistId": 3,
                      "memberId": 8589934621,
                      "memberKey": "ruru_dambara"
                    },
                    {
                      "artistId": 1,
                      "memberId": 8589934601,
                      "memberKey": "reina_yokoyama"
                    },
                    {
                      "artistId": 2,
                      "memberId": 8590783732,
                      "memberKey": "yukiho_shimoitani"
                    },
                    {
                      "artistId": 1,
                      "memberId": 8589934605,
                      "memberKey": "mei_yamazaki"
                    },
                    {
                      "artistId": 3,
                      "memberId": 8589934668,
                      "memberKey": "rei_inoue"
                    },
                    {
                      "artistId": 3,
                      "memberId": 8590783744,
                      "memberKey": "mifu_kawashima"
                    },
                    {
                      "artistId": 1,
                      "memberId": 8589934596,
                      "memberKey": "sakura_oda"
                    },
                    {
                      "artistId": 3,
                      "memberId": 8589934620,
                      "memberKey": "akari_uemura"
                    },
                    {
                      "artistId": 1,
                      "memberId": 8589934599,
                      "memberKey": "akane_haga"
                    },
                    {
                      "artistId": 7,
                      "memberId": 8589934644,
                      "memberKey": "rika_shimakura"
                    },
                    {
                      "artistId": 6,
                      "memberId": 8589934640,
                      "memberKey": "mizuho_ono"
                    },
                    {
                      "artistId": 1,
                      "memberId": 8589934597,
                      "memberKey": "miki_nonaka"
                    },
                    {
                      "artistId": 1,
                      "memberId": 8590786239,
                      "memberKey": "ako_yumigeta"
                    },
                    {
                      "artistId": 7,
                      "memberId": 8589934649,
                      "memberKey": "yuhane_yamazaki"
                    },
                    {
                      "artistId": 7,
                      "memberId": 8589934645,
                      "memberKey": "shiori_nishida"
                    },
                    {
                      "artistId": 7,
                      "memberId": 8589934650,
                      "memberKey": "minami_okamura"
                    },
                    {
                      "artistId": 2,
                      "memberId": 8589934615,
                      "memberKey": "layla_ise"
                    },
                    {
                      "artistId": 7,
                      "memberId": 8589934653,
                      "memberKey": "honoka_kobayashi"
                    },
                    {
                      "artistId": 6,
                      "memberId": 8589934641,
                      "memberKey": "saori_onoda"
                    },
                    {
                      "artistId": 7,
                      "memberId": 8589934646,
                      "memberKey": "saya_eguchi"
                    },
                    {
                      "artistId": 6,
                      "memberId": 8589934642,
                      "memberKey": "mao_akiyama"
                    },
                    {
                      "artistId": 1,
                      "memberId": 8589934604,
                      "memberKey": "homare_okamura"
                    },
                    {
                      "artistId": 1,
                      "memberId": 8589934598,
                      "memberKey": "maria_makino"
                    },
                    {
                      "artistId": 1,
                      "memberId": 8589934603,
                      "memberKey": "rio_kitagawa"
                    },
                    {
                      "artistId": 1,
                      "memberId": 8589934594,
                      "memberKey": "ayumi_ishida"
                    },
                    {
                      "artistId": 1,
                      "memberId": 8589934593,
                      "memberKey": "erina_ikuta"
                    },
                    {
                      "artistId": 8,
                      "memberId": 8590061987,
                      "memberKey": "nanami_kubota"
                    },
                    {
                      "artistId": 1,
                      "memberId": 8590222510,
                      "memberKey": "rio_sakurai"
                    },
                    {
                      "artistId": 1,
                      "memberId": 8590786238,
                      "memberKey": "haruka_inoue"
                    },
                    {
                      "artistId": 8,
                      "memberId": 8590061989,
                      "memberKey": "natsume_nakayama"
                    },
                    {
                      "artistId": 6,
                      "memberId": 8589934677,
                      "memberKey": "marine_fukuda"
                    },
                    {
                      "artistId": 6,
                      "memberId": 8590919626,
                      "memberKey": "fuka_doi"
                    },
                    {
                      "artistId": 6,
                      "memberId": 8590919624,
                      "memberKey": "mihane_ishii"
                    },
                    {
                      "artistId": 8,
                      "memberId": 8590061990,
                      "memberKey": "miku_nishizaki"
                    },
                    {
                      "artistId": 6,
                      "memberId": 8589934676,
                      "memberKey": "shiori_yagi"
                    },
                    {
                      "artistId": 2,
                      "memberId": 8589934670,
                      "memberKey": "shion_tamenaga"
                    },
                    {
                      "artistId": 6,
                      "memberId": 8589934637,
                      "memberKey": "ami_tanimoto"
                    },
                    {
                      "artistId": 2,
                      "memberId": 8589934608,
                      "memberKey": "ayano_kawamura"
                    },
                    {
                      "artistId": 7,
                      "memberId": 8589934648,
                      "memberKey": "kokoro_maeda"
                    },
                    {
                      "artistId": 2,
                      "memberId": 8590085285,
                      "memberKey": "yuki_hirayama"
                    },
                    {
                      "artistId": 2,
                      "memberId": 8590783733,
                      "memberKey": "hana_goto"
                    },
                    {
                      "artistId": 7,
                      "memberId": 8589934647,
                      "memberKey": "kurumi_takase"
                    },
                    {
                      "artistId": 8,
                      "memberId": 8590061988,
                      "memberKey": "sumire_tashiro"
                    },
                    {
                      "artistId": 6,
                      "memberId": 8590919625,
                      "memberKey": "yuu_murata"
                    },
                    {
                      "artistId": 7,
                      "memberId": 8589934652,
                      "memberKey": "miyo_hirai"
                    },
                    {
                      "artistId": 8,
                      "memberId": 8590061985,
                      "memberKey": "kanami_ishiguri"
                    },
                    {
                      "artistId": 8,
                      "memberId": 8590061992,
                      "memberKey": "roko_tsutsui"
                    },
                    {
                      "artistId": 6,
                      "memberId": 8589934675,
                      "memberKey": "yuumi_kasai"
                    },
                    {
                      "artistId": 8,
                      "memberId": 8590061986,
                      "memberKey": "kirara_yonemura"
                    },
                    {
                      "artistId": 2,
                      "memberId": 8589934611,
                      "memberKey": "moe_kamikokuryo"
                    },
                    {
                      "artistId": 6,
                      "memberId": 8589934678,
                      "memberKey": "runo_yofu"
                    },
                    {
                      "artistId": 7,
                      "memberId": 8589934654,
                      "memberKey": "utano_satoyoshi"
                    },
                    {
                      "artistId": 2,
                      "memberId": 8589934669,
                      "memberKey": "rin_kawana"
                    },
                    {
                      "artistId": 8,
                      "memberId": 8590061991,
                      "memberKey": "momo_kitahara"
                    },
                    {
                      "artistId": 8,
                      "memberId": 8590061984,
                      "memberKey": "ruli_hiromoto"
                    },
                    {
                      "artistId": 2,
                      "memberId": 8589934610,
                      "memberKey": "rikako_sasaki"
                    },
                    {
                      "artistId": 7,
                      "memberId": 8589934651,
                      "memberKey": "momohime_kiyono"
                    },
                    {
                      "artistId": 2,
                      "memberId": 8589934671,
                      "memberKey": "wakana_matsumoto"
                    },
                    {
                      "artistId": 8,
                      "memberId": 8590061983,
                      "memberKey": "madoka_saito"
                    },
                    {
                      "artistId": 2,
                      "memberId": 8589934616,
                      "memberKey": "rin_hashisako"
                    }
                  ]
                }
              }
            }
          ]
        }
      }
    }
  },
  "variables": {}
}
